safety_django/__init__.py
safety_django/admin.py
safety_django/apps.py
safety_django/models.py
safety_django/settings.py
safety_django/templates/insecure.html
safety_django/templates/admin/base.html
safety_django-0.1.1.dist-info/DESCRIPTION.rst
safety_django-0.1.1.dist-info/METADATA
safety_django-0.1.1.dist-info/RECORD
safety_django-0.1.1.dist-info/WHEEL
safety_django-0.1.1.dist-info/metadata.json
safety_django-0.1.1.dist-info/top_level.txt
