Metadata-Version: 2.0
Name: safety-django
Version: 0.1.1
Summary: safety-django checks your installed dependencies for known security vulnerabilities and displays them in the admin area.
Home-page: https://github.com/pyupio/safety_django
Author: pyup.io
Author-email: support@pyup.io
License: MIT license
Keywords: safety_django
Platform: UNKNOWN
Classifier: Development Status :: 2 - Pre-Alpha
Classifier: Intended Audience :: Developers
Classifier: License :: OSI Approved :: MIT License
Classifier: Natural Language :: English
Classifier: Programming Language :: Python :: 2
Classifier: Programming Language :: Python :: 2.6
Classifier: Programming Language :: Python :: 2.7
Classifier: Programming Language :: Python :: 3
Classifier: Programming Language :: Python :: 3.3
Classifier: Programming Language :: Python :: 3.4
Classifier: Programming Language :: Python :: 3.5
Requires-Dist: safety
